{
    "template_key": "nortwest",
    "page_width": 594.96,
    "page_height": 842.25,
    "pages": [
        {
            "page": 1,
            "image": "images/forms/nortwest/page-1.png"
        },
        {
            "page": 2,
            "image": "images/forms/nortwest/page-2.png"
        },
        {
            "page": 3,
            "image": "images/forms/nortwest/page-3.png"
        },
        {
            "page": 4,
            "image": "images/forms/nortwest/page-4.png"
        }
    ],
    "fields": [
        {
            "key": "text1",
            "label": "Text1",
            "type": "text",
            "page": 1,
            "rect": [
                118.902,
                680.779,
                271.951,
                694.803
            ],
            "field_type": "/Tx",
            "field_flags": 0
        },
        {
            "key": "text8",
            "label": "Text8",
            "type": "text",
            "page": 1,
            "rect": [
                243,
                647,
                257.151,
                655.491
            ],
            "field_type": "/Tx",
            "field_flags": 0
        },
        {
            "key": "text16",
            "label": "Text16",
            "type": "text",
            "page": 1,
            "rect": [
                133.019,
                561.678,
                271.226,
                572.999
            ],
            "field_type": "/Tx",
            "field_flags": 0
        },
        {
            "key": "text23",
            "label": "Text23",
            "type": "text",
            "page": 1,
            "rect": [
                100,
                493.282,
                181.132,
                505.074
            ],
            "field_type": "/Tx",
            "field_flags": 0
        },
        {
            "key": "text24",
            "label": "Text24",
            "type": "text",
            "page": 1,
            "rect": [
                210.849,
                492.81,
                275.943,
                504.131
            ],
            "field_type": "/Tx",
            "field_flags": 0
        },
        {
            "key": "text25",
            "label": "Text25",
            "type": "text",
            "page": 1,
            "rect": [
                101.887,
                476.301,
                166.981,
                487.621
            ],
            "field_type": "/Tx",
            "field_flags": 0
        },
        {
            "key": "text26",
            "label": "Text26",
            "type": "text",
            "page": 1,
            "rect": [
                211.792,
                475.829,
                275.943,
                486.206
            ],
            "field_type": "/Tx",
            "field_flags": 0
        },
        {
            "key": "text27",
            "label": "Text27",
            "type": "text",
            "page": 1,
            "rect": [
                412.736,
                569.225,
                476.415,
                580.074
            ],
            "field_type": "/Tx",
            "field_flags": 0
        },
        {
            "key": "text28",
            "label": "Text28",
            "type": "text",
            "page": 1,
            "rect": [
                317.925,
                436.206,
                419.811,
                444.697
            ],
            "field_type": "/Tx",
            "field_flags": 0
        },
        {
            "key": "text30",
            "label": "Text30",
            "type": "text",
            "page": 1,
            "rect": [
                358.491,
                405.074,
                370.755,
                414.98
            ],
            "field_type": "/Tx",
            "field_flags": 0
        },
        {
            "key": "text31",
            "label": "Text31",
            "type": "text",
            "page": 1,
            "rect": [
                376.415,
                405.074,
                390.094,
                414.508
            ],
            "field_type": "/Tx",
            "field_flags": 0
        },
        {
            "key": "text32",
            "label": "Text32",
            "type": "text",
            "page": 1,
            "rect": [
                395.283,
                405.074,
                407.547,
                414.508
            ],
            "field_type": "/Tx",
            "field_flags": 0
        },
        {
            "key": "text33",
            "label": "Text33",
            "type": "text",
            "page": 1,
            "rect": [
                53.7736,
                436.678,
                154.717,
                447.527
            ],
            "field_type": "/Tx",
            "field_flags": 0
        },
        {
            "key": "text34",
            "label": "Text34",
            "type": "text",
            "page": 1,
            "rect": [
                73.5849,
                419.697,
                154.245,
                429.131
            ],
            "field_type": "/Tx",
            "field_flags": 0
        },
        {
            "key": "text36",
            "label": "Text36",
            "type": "text",
            "page": 1,
            "rect": [
                228.774,
                434.319,
                282.075,
                446.112
            ],
            "field_type": "/Tx",
            "field_flags": 0
        },
        {
            "key": "text37",
            "label": "Text37",
            "type": "text",
            "page": 1,
            "rect": [
                208.491,
                417.338,
                282.075,
                427.716
            ],
            "field_type": "/Tx",
            "field_flags": 0
        },
        {
            "key": "text38",
            "label": "Text38",
            "type": "text",
            "page": 1,
            "rect": [
                177.358,
                339.98,
                272.642,
                353.187
            ],
            "field_type": "/Tx",
            "field_flags": 0
        },
        {
            "key": "text39",
            "label": "Text39",
            "type": "text",
            "page": 1,
            "rect": [
                466.509,
                256.018,
                546.698,
                265.923
            ],
            "field_type": "/Tx",
            "field_flags": 0
        },
        {
            "key": "text40",
            "label": "Text40",
            "type": "text",
            "page": 1,
            "rect": [
                94.8113,
                291.395,
                271.698,
                304.131
            ],
            "field_type": "/Tx",
            "field_flags": 0
        },
        {
            "key": "text41",
            "label": "Text41",
            "type": "text",
            "page": 1,
            "rect": [
                75.4717,
                276.772,
                271.226,
                287.15
            ],
            "field_type": "/Tx",
            "field_flags": 0
        },
        {
            "key": "text42",
            "label": "Text42",
            "type": "text",
            "page": 1,
            "rect": [
                100.943,
                262.15,
                269.811,
                273.47
            ],
            "field_type": "/Tx",
            "field_flags": 0
        },
        {
            "key": "text43",
            "label": "Text43",
            "type": "text",
            "page": 1,
            "rect": [
                134.906,
                201.772,
                273.113,
                213.565
            ],
            "field_type": "/Tx",
            "field_flags": 0
        },
        {
            "key": "button80",
            "label": "Button80",
            "type": "checkbox",
            "page": 1,
            "rect": [
                314.245,
                668.282,
                329.245,
                683.282
            ],
            "field_type": "/Btn",
            "field_flags": 0
        },
        {
            "key": "button81",
            "label": "Button81",
            "type": "checkbox",
            "page": 1,
            "rect": [
                365.66,
                668.282,
                380.66,
                683.282
            ],
            "field_type": "/Btn",
            "field_flags": 0
        },
        {
            "key": "button84",
            "label": "Button84",
            "type": "checkbox",
            "page": 1,
            "rect": [
                314.245,
                567.15,
                329.245,
                582.15
            ],
            "field_type": "/Btn",
            "field_flags": 0
        },
        {
            "key": "button85",
            "label": "Button85",
            "type": "checkbox",
            "page": 1,
            "rect": [
                495.377,
                567.15,
                510.377,
                582.15
            ],
            "field_type": "/Btn",
            "field_flags": 0
        },
        {
            "key": "button86",
            "label": "Button86",
            "type": "checkbox",
            "page": 1,
            "rect": [
                314.245,
                339.98,
                329.245,
                354.98
            ],
            "field_type": "/Btn",
            "field_flags": 0
        },
        {
            "key": "button87",
            "label": "Button87",
            "type": "checkbox",
            "page": 1,
            "rect": [
                314.245,
                311.678,
                329.245,
                326.678
            ],
            "field_type": "/Btn",
            "field_flags": 0
        },
        {
            "key": "button97",
            "label": "Button97",
            "type": "checkbox",
            "page": 1,
            "rect": [
                391.981,
                264.036,
                404.717,
                276.772
            ],
            "field_type": "/Btn",
            "field_flags": 0
        },
        {
            "key": "button98",
            "label": "Button98",
            "type": "checkbox",
            "page": 1,
            "rect": [
                444.34,
                264.036,
                456.604,
                276.301
            ],
            "field_type": "/Btn",
            "field_flags": 0
        },
        {
            "key": "button99",
            "label": "Button99",
            "type": "checkbox",
            "page": 1,
            "rect": [
                177.358,
                243.848,
                192.358,
                258.848
            ],
            "field_type": "/Btn",
            "field_flags": 0
        },
        {
            "key": "button100",
            "label": "Button100",
            "type": "checkbox",
            "page": 1,
            "rect": [
                232.641,
                243.848,
                247.642,
                258.848
            ],
            "field_type": "/Btn",
            "field_flags": 0
        },
        {
            "key": "button101",
            "label": "Button101",
            "type": "checkbox",
            "page": 1,
            "rect": [
                18.0189,
                212.621,
                33.0189,
                227.621
            ],
            "field_type": "/Btn",
            "field_flags": 0
        },
        {
            "key": "button102",
            "label": "Button102",
            "type": "checkbox",
            "page": 1,
            "rect": [
                64.717,
                212.621,
                79.717,
                227.621
            ],
            "field_type": "/Btn",
            "field_flags": 0
        },
        {
            "key": "button103",
            "label": "Button103",
            "type": "checkbox",
            "page": 1,
            "rect": [
                314.245,
                201.772,
                329.245,
                216.772
            ],
            "field_type": "/Btn",
            "field_flags": 0
        },
        {
            "key": "button104",
            "label": "Button104",
            "type": "checkbox",
            "page": 1,
            "rect": [
                389.717,
                201.772,
                404.717,
                216.772
            ],
            "field_type": "/Btn",
            "field_flags": 0
        },
        {
            "key": "button105",
            "label": "Button105",
            "type": "checkbox",
            "page": 1,
            "rect": [
                18.0189,
                106.018,
                33.0189,
                121.018
            ],
            "field_type": "/Btn",
            "field_flags": 0
        },
        {
            "key": "button106",
            "label": "Button106",
            "type": "checkbox",
            "page": 1,
            "rect": [
                18.0189,
                79.6026,
                33.0189,
                94.6026
            ],
            "field_type": "/Btn",
            "field_flags": 0
        },
        {
            "key": "button107",
            "label": "Button107",
            "type": "checkbox",
            "page": 1,
            "rect": [
                18.0189,
                53.1875,
                33.0189,
                68.1875
            ],
            "field_type": "/Btn",
            "field_flags": 0
        },
        {
            "key": "button163",
            "label": "Button163",
            "type": "checkbox",
            "page": 1,
            "rect": [
                18.0189,
                338.187,
                33.0189,
                353.187
            ],
            "field_type": "/Btn",
            "field_flags": 0
        },
        {
            "key": "button164",
            "label": "Button164",
            "type": "checkbox",
            "page": 1,
            "rect": [
                61.4151,
                338.187,
                76.4151,
                353.187
            ],
            "field_type": "/Btn",
            "field_flags": 0
        },
        {
            "key": "text182",
            "label": "Text182",
            "type": "text",
            "page": 1,
            "rect": [
                88,
                663,
                270.625,
                675.375
            ],
            "field_type": "/Tx",
            "field_flags": 0
        },
        {
            "key": "text185",
            "label": "Text185",
            "type": "text",
            "page": 1,
            "rect": [
                72.375,
                612.07,
                161.25,
                623.695
            ],
            "field_type": "/Tx",
            "field_flags": 0
        },
        {
            "key": "text186",
            "label": "Text186",
            "type": "text",
            "page": 1,
            "rect": [
                46.875,
                595.195,
                270,
                608.32
            ],
            "field_type": "/Tx",
            "field_flags": 0
        },
        {
            "key": "text188",
            "label": "Text188",
            "type": "text",
            "page": 1,
            "rect": [
                53.625,
                577.57,
                270,
                591.445
            ],
            "field_type": "/Tx",
            "field_flags": 0
        },
        {
            "key": "text189",
            "label": "Text189",
            "type": "text",
            "page": 1,
            "rect": [
                100.875,
                544.945,
                179.625,
                557.695
            ],
            "field_type": "/Tx",
            "field_flags": 0
        },
        {
            "key": "text190",
            "label": "Text190",
            "type": "text",
            "page": 1,
            "rect": [
                210.375,
                544.57,
                276.75,
                557.32
            ],
            "field_type": "/Tx",
            "field_flags": 0
        },
        {
            "key": "text191",
            "label": "Text191",
            "type": "text",
            "page": 1,
            "rect": [
                210.375,
                527.695,
                276.375,
                538.195
            ],
            "field_type": "/Tx",
            "field_flags": 0
        },
        {
            "key": "text194",
            "label": "Text194",
            "type": "text",
            "page": 1,
            "rect": [
                164.625,
                510.07,
                273.75,
                520.945
            ],
            "field_type": "/Tx",
            "field_flags": 0
        },
        {
            "key": "text195",
            "label": "Text195",
            "type": "text",
            "page": 1,
            "rect": [
                96.6981,
                631.018,
                187.264,
                643.282
            ],
            "field_type": "/Tx",
            "field_flags": 0
        },
        {
            "key": "text197",
            "label": "Text197",
            "type": "text",
            "page": 1,
            "rect": [
                100.472,
                527.716,
                165.094,
                539.037
            ],
            "field_type": "/Tx",
            "field_flags": 0
        },
        {
            "key": "text_field_2024_06_06_01_57_28_5365",
            "label": "Text Field_2024-06-06 01:57:28 5365",
            "type": "text",
            "page": 1,
            "rect": [
                80,
                645,
                91.7924,
                653.491
            ],
            "field_type": "/Tx",
            "field_flags": 0
        },
        {
            "key": "text_field_2024_06_06_01_57_34_2082",
            "label": "Text Field_2024-06-06 01:57:34 2082",
            "type": "text",
            "page": 1,
            "rect": [
                153,
                645,
                164.792,
                653.491
            ],
            "field_type": "/Tx",
            "field_flags": 0
        },
        {
            "key": "text_field_2024_06_06_01_57_50_9852",
            "label": "Text Field_2024-06-06 01:57:50 9852",
            "type": "text",
            "page": 1,
            "rect": [
                118,
                645,
                129.792,
                653.491
            ],
            "field_type": "/Tx",
            "field_flags": 0
        },
        {
            "key": "text_field_2024_06_06_06_53_34_7826",
            "label": "Text Field_2024-06-06 06:53:34 7826",
            "type": "text",
            "page": 1,
            "rect": [
                225,
                647,
                239.151,
                655.491
            ],
            "field_type": "/Tx",
            "field_flags": 0
        },
        {
            "key": "text_field_2024_06_06_06_53_40_3512",
            "label": "Text Field_2024-06-06 06:53:40 3512",
            "type": "text",
            "page": 1,
            "rect": [
                260,
                647,
                274.151,
                655.491
            ],
            "field_type": "/Tx",
            "field_flags": 0
        },
        {
            "key": "text54",
            "label": "Text54",
            "type": "text",
            "page": 2,
            "rect": [
                383.962,
                626.772,
                469.811,
                645.64
            ],
            "field_type": "/Tx",
            "field_flags": 0
        },
        {
            "key": "text55",
            "label": "Text55",
            "type": "text",
            "page": 2,
            "rect": [
                384.906,
                601.301,
                468.396,
                620.169
            ],
            "field_type": "/Tx",
            "field_flags": 0
        },
        {
            "key": "text59",
            "label": "Text59",
            "type": "text",
            "page": 2,
            "rect": [
                478.774,
                626.772,
                565.566,
                644.697
            ],
            "field_type": "/Tx",
            "field_flags": 0
        },
        {
            "key": "text61",
            "label": "Text61",
            "type": "text",
            "page": 2,
            "rect": [
                478.302,
                601.772,
                566.038,
                620.169
            ],
            "field_type": "/Tx",
            "field_flags": 0
        },
        {
            "key": "button108",
            "label": "Button108",
            "type": "checkbox",
            "page": 2,
            "rect": [
                150.094,
                679.131,
                165.094,
                694.131
            ],
            "field_type": "/Btn",
            "field_flags": 0
        },
        {
            "key": "button109",
            "label": "Button109",
            "type": "checkbox",
            "page": 2,
            "rect": [
                238.302,
                679.131,
                253.302,
                694.131
            ],
            "field_type": "/Btn",
            "field_flags": 0
        },
        {
            "key": "button110",
            "label": "Button110",
            "type": "checkbox",
            "page": 2,
            "rect": [
                304.811,
                679.131,
                319.811,
                694.131
            ],
            "field_type": "/Btn",
            "field_flags": 0
        },
        {
            "key": "button111",
            "label": "Button111",
            "type": "checkbox",
            "page": 2,
            "rect": [
                155.283,
                657.433,
                170.283,
                672.433
            ],
            "field_type": "/Btn",
            "field_flags": 0
        },
        {
            "key": "button112",
            "label": "Button112",
            "type": "checkbox",
            "page": 2,
            "rect": [
                226.509,
                657.433,
                241.509,
                672.433
            ],
            "field_type": "/Btn",
            "field_flags": 0
        },
        {
            "key": "button113",
            "label": "Button113",
            "type": "checkbox",
            "page": 2,
            "rect": [
                308.585,
                657.433,
                323.585,
                672.433
            ],
            "field_type": "/Btn",
            "field_flags": 0
        },
        {
            "key": "button114",
            "label": "Button114",
            "type": "checkbox",
            "page": 2,
            "rect": [
                431.698,
                489.036,
                446.698,
                504.036
            ],
            "field_type": "/Btn",
            "field_flags": 0
        },
        {
            "key": "button115",
            "label": "Button115",
            "type": "checkbox",
            "page": 2,
            "rect": [
                431.698,
                457.433,
                446.698,
                472.433
            ],
            "field_type": "/Btn",
            "field_flags": 0
        },
        {
            "key": "button116",
            "label": "Button116",
            "type": "checkbox",
            "page": 2,
            "rect": [
                431.698,
                425.829,
                446.698,
                440.829
            ],
            "field_type": "/Btn",
            "field_flags": 0
        },
        {
            "key": "button117",
            "label": "Button117",
            "type": "checkbox",
            "page": 2,
            "rect": [
                484.057,
                489.036,
                499.057,
                504.036
            ],
            "field_type": "/Btn",
            "field_flags": 0
        },
        {
            "key": "button118",
            "label": "Button118",
            "type": "checkbox",
            "page": 2,
            "rect": [
                539.717,
                489.036,
                554.717,
                504.036
            ],
            "field_type": "/Btn",
            "field_flags": 0
        },
        {
            "key": "button119",
            "label": "Button119",
            "type": "checkbox",
            "page": 2,
            "rect": [
                484.057,
                457.433,
                499.057,
                472.433
            ],
            "field_type": "/Btn",
            "field_flags": 0
        },
        {
            "key": "button120",
            "label": "Button120",
            "type": "checkbox",
            "page": 2,
            "rect": [
                539.717,
                457.433,
                554.717,
                472.433
            ],
            "field_type": "/Btn",
            "field_flags": 0
        },
        {
            "key": "button121",
            "label": "Button121",
            "type": "checkbox",
            "page": 2,
            "rect": [
                539.717,
                425.829,
                554.717,
                440.829
            ],
            "field_type": "/Btn",
            "field_flags": 0
        },
        {
            "key": "button122",
            "label": "Button122",
            "type": "checkbox",
            "page": 2,
            "rect": [
                484.057,
                425.829,
                499.057,
                440.829
            ],
            "field_type": "/Btn",
            "field_flags": 0
        },
        {
            "key": "button123",
            "label": "Button123",
            "type": "checkbox",
            "page": 2,
            "rect": [
                484.057,
                394.225,
                499.057,
                409.225
            ],
            "field_type": "/Btn",
            "field_flags": 0
        },
        {
            "key": "button124",
            "label": "Button124",
            "type": "checkbox",
            "page": 2,
            "rect": [
                539.717,
                394.225,
                554.717,
                409.225
            ],
            "field_type": "/Btn",
            "field_flags": 0
        },
        {
            "key": "button125",
            "label": "Button125",
            "type": "checkbox",
            "page": 2,
            "rect": [
                431.698,
                394.225,
                446.698,
                409.225
            ],
            "field_type": "/Btn",
            "field_flags": 0
        },
        {
            "key": "button126",
            "label": "Button126",
            "type": "checkbox",
            "page": 2,
            "rect": [
                431.698,
                362.621,
                446.698,
                377.621
            ],
            "field_type": "/Btn",
            "field_flags": 0
        },
        {
            "key": "button127",
            "label": "Button127",
            "type": "checkbox",
            "page": 2,
            "rect": [
                484.057,
                362.621,
                499.057,
                377.621
            ],
            "field_type": "/Btn",
            "field_flags": 0
        },
        {
            "key": "button128",
            "label": "Button128",
            "type": "checkbox",
            "page": 2,
            "rect": [
                539.717,
                362.621,
                554.717,
                377.621
            ],
            "field_type": "/Btn",
            "field_flags": 0
        },
        {
            "key": "button129",
            "label": "Button129",
            "type": "checkbox",
            "page": 2,
            "rect": [
                539.717,
                331.018,
                554.717,
                346.018
            ],
            "field_type": "/Btn",
            "field_flags": 0
        },
        {
            "key": "button130",
            "label": "Button130",
            "type": "checkbox",
            "page": 2,
            "rect": [
                484.057,
                331.018,
                499.057,
                346.018
            ],
            "field_type": "/Btn",
            "field_flags": 0
        },
        {
            "key": "button131",
            "label": "Button131",
            "type": "checkbox",
            "page": 2,
            "rect": [
                431.698,
                331.018,
                446.698,
                346.018
            ],
            "field_type": "/Btn",
            "field_flags": 0
        },
        {
            "key": "button132",
            "label": "Button132",
            "type": "checkbox",
            "page": 2,
            "rect": [
                431.698,
                299.414,
                446.698,
                314.414
            ],
            "field_type": "/Btn",
            "field_flags": 0
        },
        {
            "key": "button133",
            "label": "Button133",
            "type": "checkbox",
            "page": 2,
            "rect": [
                431.698,
                267.81,
                446.698,
                282.81
            ],
            "field_type": "/Btn",
            "field_flags": 0
        },
        {
            "key": "button134",
            "label": "Button134",
            "type": "checkbox",
            "page": 2,
            "rect": [
                484.057,
                299.414,
                499.057,
                314.414
            ],
            "field_type": "/Btn",
            "field_flags": 0
        },
        {
            "key": "button135",
            "label": "Button135",
            "type": "checkbox",
            "page": 2,
            "rect": [
                539.717,
                299.414,
                554.717,
                314.414
            ],
            "field_type": "/Btn",
            "field_flags": 0
        },
        {
            "key": "button136",
            "label": "Button136",
            "type": "checkbox",
            "page": 2,
            "rect": [
                484.057,
                267.81,
                499.057,
                282.81
            ],
            "field_type": "/Btn",
            "field_flags": 0
        },
        {
            "key": "button137",
            "label": "Button137",
            "type": "checkbox",
            "page": 2,
            "rect": [
                539.717,
                267.81,
                554.717,
                282.81
            ],
            "field_type": "/Btn",
            "field_flags": 0
        },
        {
            "key": "button138",
            "label": "Button138",
            "type": "checkbox",
            "page": 2,
            "rect": [
                431.698,
                236.206,
                446.698,
                251.206
            ],
            "field_type": "/Btn",
            "field_flags": 0
        },
        {
            "key": "button139",
            "label": "Button139",
            "type": "checkbox",
            "page": 2,
            "rect": [
                431.698,
                204.602,
                446.698,
                219.602
            ],
            "field_type": "/Btn",
            "field_flags": 0
        },
        {
            "key": "button140",
            "label": "Button140",
            "type": "checkbox",
            "page": 2,
            "rect": [
                431.698,
                172.999,
                446.698,
                187.999
            ],
            "field_type": "/Btn",
            "field_flags": 0
        },
        {
            "key": "button141",
            "label": "Button141",
            "type": "checkbox",
            "page": 2,
            "rect": [
                431.698,
                141.395,
                446.698,
                156.395
            ],
            "field_type": "/Btn",
            "field_flags": 0
        },
        {
            "key": "button142",
            "label": "Button142",
            "type": "checkbox",
            "page": 2,
            "rect": [
                431.698,
                109.791,
                446.698,
                124.791
            ],
            "field_type": "/Btn",
            "field_flags": 0
        },
        {
            "key": "button143",
            "label": "Button143",
            "type": "checkbox",
            "page": 2,
            "rect": [
                431.698,
                78.187,
                446.698,
                93.187
            ],
            "field_type": "/Btn",
            "field_flags": 0
        },
        {
            "key": "button144",
            "label": "Button144",
            "type": "checkbox",
            "page": 2,
            "rect": [
                431.698,
                46.583,
                446.698,
                61.583
            ],
            "field_type": "/Btn",
            "field_flags": 0
        },
        {
            "key": "button148",
            "label": "Button148",
            "type": "checkbox",
            "page": 2,
            "rect": [
                539.717,
                46.583,
                554.717,
                61.583
            ],
            "field_type": "/Btn",
            "field_flags": 0
        },
        {
            "key": "button149",
            "label": "Button149",
            "type": "checkbox",
            "page": 2,
            "rect": [
                484.057,
                46.583,
                499.057,
                61.583
            ],
            "field_type": "/Btn",
            "field_flags": 0
        },
        {
            "key": "button150",
            "label": "Button150",
            "type": "checkbox",
            "page": 2,
            "rect": [
                484.057,
                78.187,
                499.057,
                93.187
            ],
            "field_type": "/Btn",
            "field_flags": 0
        },
        {
            "key": "button151",
            "label": "Button151",
            "type": "checkbox",
            "page": 2,
            "rect": [
                539.717,
                78.187,
                554.717,
                93.187
            ],
            "field_type": "/Btn",
            "field_flags": 0
        },
        {
            "key": "button152",
            "label": "Button152",
            "type": "checkbox",
            "page": 2,
            "rect": [
                539.717,
                109.791,
                554.717,
                124.791
            ],
            "field_type": "/Btn",
            "field_flags": 0
        },
        {
            "key": "button153",
            "label": "Button153",
            "type": "checkbox",
            "page": 2,
            "rect": [
                484.057,
                109.791,
                499.057,
                124.791
            ],
            "field_type": "/Btn",
            "field_flags": 0
        },
        {
            "key": "button154",
            "label": "Button154",
            "type": "checkbox",
            "page": 2,
            "rect": [
                484.057,
                141.395,
                499.057,
                156.395
            ],
            "field_type": "/Btn",
            "field_flags": 0
        },
        {
            "key": "button155",
            "label": "Button155",
            "type": "checkbox",
            "page": 2,
            "rect": [
                539.717,
                141.395,
                554.717,
                156.395
            ],
            "field_type": "/Btn",
            "field_flags": 0
        },
        {
            "key": "button156",
            "label": "Button156",
            "type": "checkbox",
            "page": 2,
            "rect": [
                539.717,
                172.999,
                554.717,
                187.999
            ],
            "field_type": "/Btn",
            "field_flags": 0
        },
        {
            "key": "button157",
            "label": "Button157",
            "type": "checkbox",
            "page": 2,
            "rect": [
                484.057,
                172.999,
                499.057,
                187.999
            ],
            "field_type": "/Btn",
            "field_flags": 0
        },
        {
            "key": "button158",
            "label": "Button158",
            "type": "checkbox",
            "page": 2,
            "rect": [
                484.057,
                204.602,
                499.057,
                219.602
            ],
            "field_type": "/Btn",
            "field_flags": 0
        },
        {
            "key": "button160",
            "label": "Button160",
            "type": "checkbox",
            "page": 2,
            "rect": [
                539.717,
                204.602,
                554.717,
                219.602
            ],
            "field_type": "/Btn",
            "field_flags": 0
        },
        {
            "key": "button161",
            "label": "Button161",
            "type": "checkbox",
            "page": 2,
            "rect": [
                539.717,
                236.206,
                554.717,
                251.206
            ],
            "field_type": "/Btn",
            "field_flags": 0
        },
        {
            "key": "button162",
            "label": "Button162",
            "type": "checkbox",
            "page": 2,
            "rect": [
                484.057,
                236.206,
                499.057,
                251.206
            ],
            "field_type": "/Btn",
            "field_flags": 0
        },
        {
            "key": "button165",
            "label": "Button165",
            "type": "checkbox",
            "page": 2,
            "rect": [
                419.151,
                579.697,
                434.151,
                594.697
            ],
            "field_type": "/Btn",
            "field_flags": 0
        },
        {
            "key": "button166",
            "label": "Button166",
            "type": "checkbox",
            "page": 2,
            "rect": [
                419.151,
                550.829,
                434.151,
                565.829
            ],
            "field_type": "/Btn",
            "field_flags": 0
        },
        {
            "key": "button167",
            "label": "Button167",
            "type": "checkbox",
            "page": 2,
            "rect": [
                514.67,
                550.829,
                529.67,
                565.829
            ],
            "field_type": "/Btn",
            "field_flags": 0
        },
        {
            "key": "button168",
            "label": "Button168",
            "type": "checkbox",
            "page": 2,
            "rect": [
                514.67,
                579.697,
                529.67,
                594.697
            ],
            "field_type": "/Btn",
            "field_flags": 0
        },
        {
            "key": "text66",
            "label": "Text66",
            "type": "text",
            "page": 3,
            "rect": [
                184.906,
                503.659,
                334.906,
                514.98
            ],
            "field_type": "/Tx",
            "field_flags": 0
        },
        {
            "key": "text67",
            "label": "Text67",
            "type": "text",
            "page": 3,
            "rect": [
                91.0377,
                486.678,
                334.906,
                498.942
            ],
            "field_type": "/Tx",
            "field_flags": 0
        },
        {
            "key": "text68",
            "label": "Text68",
            "type": "text",
            "page": 3,
            "rect": [
                103.302,
                469.225,
                334.434,
                480.546
            ],
            "field_type": "/Tx",
            "field_flags": 0
        },
        {
            "key": "text69",
            "label": "Text69",
            "type": "text",
            "page": 3,
            "rect": [
                71.2264,
                450.357,
                334.434,
                462.621
            ],
            "field_type": "/Tx",
            "field_flags": 0
        },
        {
            "key": "text70",
            "label": "Text70",
            "type": "textarea",
            "page": 3,
            "rect": [
                115.566,
                254.603,
                302.83,
                276.772
            ],
            "field_type": "/Tx",
            "field_flags": 0
        },
        {
            "key": "text71",
            "label": "Text71",
            "type": "text",
            "page": 3,
            "rect": [
                53.3019,
                235.263,
                73.1132,
                246.584
            ],
            "field_type": "/Tx",
            "field_flags": 0
        },
        {
            "key": "text74",
            "label": "Text74",
            "type": "text",
            "page": 3,
            "rect": [
                78.7736,
                235.263,
                102.358,
                246.584
            ],
            "field_type": "/Tx",
            "field_flags": 0
        },
        {
            "key": "text75",
            "label": "Text75",
            "type": "text",
            "page": 3,
            "rect": [
                107.076,
                235.263,
                128.302,
                245.64
            ],
            "field_type": "/Tx",
            "field_flags": 0
        },
        {
            "key": "button169",
            "label": "Button169",
            "type": "checkbox",
            "page": 3,
            "rect": [
                425.094,
                672.055,
                440.094,
                687.055
            ],
            "field_type": "/Btn",
            "field_flags": 0
        },
        {
            "key": "button170",
            "label": "Button170",
            "type": "checkbox",
            "page": 3,
            "rect": [
                425.094,
                635.735,
                440.094,
                650.735
            ],
            "field_type": "/Btn",
            "field_flags": 0
        },
        {
            "key": "button171",
            "label": "Button171",
            "type": "checkbox",
            "page": 3,
            "rect": [
                425.094,
                599.414,
                440.094,
                614.414
            ],
            "field_type": "/Btn",
            "field_flags": 0
        },
        {
            "key": "button172",
            "label": "Button172",
            "type": "checkbox",
            "page": 3,
            "rect": [
                425.094,
                566.395,
                440.094,
                581.395
            ],
            "field_type": "/Btn",
            "field_flags": 0
        },
        {
            "key": "button173",
            "label": "Button173",
            "type": "checkbox",
            "page": 3,
            "rect": [
                483.585,
                566.395,
                498.585,
                581.395
            ],
            "field_type": "/Btn",
            "field_flags": 0
        },
        {
            "key": "button174",
            "label": "Button174",
            "type": "checkbox",
            "page": 3,
            "rect": [
                546.321,
                566.395,
                561.321,
                581.395
            ],
            "field_type": "/Btn",
            "field_flags": 0
        },
        {
            "key": "button175",
            "label": "Button175",
            "type": "checkbox",
            "page": 3,
            "rect": [
                546.321,
                599.414,
                561.321,
                614.414
            ],
            "field_type": "/Btn",
            "field_flags": 0
        },
        {
            "key": "button176",
            "label": "Button176",
            "type": "checkbox",
            "page": 3,
            "rect": [
                483.585,
                599.414,
                498.585,
                614.414
            ],
            "field_type": "/Btn",
            "field_flags": 0
        },
        {
            "key": "button177",
            "label": "Button177",
            "type": "checkbox",
            "page": 3,
            "rect": [
                483.585,
                635.735,
                498.585,
                650.735
            ],
            "field_type": "/Btn",
            "field_flags": 0
        },
        {
            "key": "button178",
            "label": "Button178",
            "type": "checkbox",
            "page": 3,
            "rect": [
                546.321,
                635.735,
                561.321,
                650.735
            ],
            "field_type": "/Btn",
            "field_flags": 0
        },
        {
            "key": "button179",
            "label": "Button179",
            "type": "checkbox",
            "page": 3,
            "rect": [
                546.321,
                672.055,
                561.321,
                687.055
            ],
            "field_type": "/Btn",
            "field_flags": 0
        },
        {
            "key": "button180",
            "label": "Button180",
            "type": "checkbox",
            "page": 3,
            "rect": [
                483.585,
                672.055,
                498.585,
                687.055
            ],
            "field_type": "/Btn",
            "field_flags": 0
        },
        {
            "key": "button181",
            "label": "Button181",
            "type": "checkbox",
            "page": 3,
            "rect": [
                23.2076,
                413.625,
                38.2076,
                428.625
            ],
            "field_type": "/Btn",
            "field_flags": 0
        }
    ]
}